<?xml version="1.0" encoding="UTF-8"?>
<lista-estructuras><dominio-padre>TIPO_ACCION</dominio-padre><lista xsi:type="java:org.exolab.castor.mapping.MapItem" xmlns:xsi="http://www.w3.org/2001/XMLSchema-instance"><key xsi:type="java:java.lang.String">714</key><value force-delete="false" type="7" xsi:type="java:com.geopista.protocol.administrador.dominios.DomainNode"><id-muni>77</id-muni><patron>3</patron><first-term>Anotación</first-term><id-node>714</id-node><id-des>318</id-des><h-dict xsi:type="java:org.exolab.castor.mapping.MapItem"><key xsi:type="java:java.lang.String">gl_ES</key><value xsi:type="java:java.lang.String">Anotación</value></h-dict><h-dict xsi:type="java:org.exolab.castor.mapping.MapItem"><key xsi:type="java:java.lang.String">es_ES</key><value xsi:type="java:java.lang.String">Anotación</value></h-dict><h-dict xsi:type="java:org.exolab.castor.mapping.MapItem"><key xsi:type="java:java.lang.String">va_ES</key><value xsi:type="java:java.lang.String">Anotació</value></h-dict><h-dict xsi:type="java:org.exolab.castor.mapping.MapItem"><key xsi:type="java:java.lang.String">ca_ES</key><value xsi:type="java:java.lang.String">Anotació</value></h-dict><id-domain>145</id-domain><l-hijos/></value></lista><lista xsi:type="java:org.exolab.castor.mapping.MapItem" xmlns:xsi="http://www.w3.org/2001/XMLSchema-instance"><key xsi:type="java:java.lang.String">709</key><value force-delete="false" type="7" xsi:type="java:com.geopista.protocol.administrador.dominios.DomainNode"><id-muni>77</id-muni><patron>0</patron><first-term>Engadir</first-term><id-node>709</id-node><id-des>296</id-des><h-dict xsi:type="java:org.exolab.castor.mapping.MapItem"><key xsi:type="java:java.lang.String">gl_ES</key><value xsi:type="java:java.lang.String">Engadir</value></h-dict><h-dict xsi:type="java:org.exolab.castor.mapping.MapItem"><key xsi:type="java:java.lang.String">es_ES</key><value xsi:type="java:java.lang.String">Añadir</value></h-dict><h-dict xsi:type="java:org.exolab.castor.mapping.MapItem"><key xsi:type="java:java.lang.String">va_ES</key><value xsi:type="java:java.lang.String">Afegir</value></h-dict><h-dict xsi:type="java:org.exolab.castor.mapping.MapItem"><key xsi:type="java:java.lang.String">ca_ES</key><value xsi:type="java:java.lang.String">Afegir</value></h-dict><id-domain>145</id-domain><l-hijos/></value></lista><lista xsi:type="java:org.exolab.castor.mapping.MapItem" xmlns:xsi="http://www.w3.org/2001/XMLSchema-instance"><key xsi:type="java:java.lang.String">708</key><value force-delete="false" type="7" xsi:type="java:com.geopista.protocol.administrador.dominios.DomainNode"><id-muni>77</id-muni><patron>1</patron><first-term>Borrar</first-term><id-node>708</id-node><id-des>295</id-des><h-dict xsi:type="java:org.exolab.castor.mapping.MapItem"><key xsi:type="java:java.lang.String">gl_ES</key><value xsi:type="java:java.lang.String">Borrar</value></h-dict><h-dict xsi:type="java:org.exolab.castor.mapping.MapItem"><key xsi:type="java:java.lang.String">es_ES</key><value xsi:type="java:java.lang.String">Borrar</value></h-dict><h-dict xsi:type="java:org.exolab.castor.mapping.MapItem"><key xsi:type="java:java.lang.String">va_ES</key><value xsi:type="java:java.lang.String">Esborrar</value></h-dict><h-dict xsi:type="java:org.exolab.castor.mapping.MapItem"><key xsi:type="java:java.lang.String">ca_ES</key><value xsi:type="java:java.lang.String">Esborrar</value></h-dict><id-domain>145</id-domain><l-hijos/></value></lista><lista xsi:type="java:org.exolab.castor.mapping.MapItem" xmlns:xsi="http://www.w3.org/2001/XMLSchema-instance"><key xsi:type="java:java.lang.String">707</key><value force-delete="false" type="7" xsi:type="java:com.geopista.protocol.administrador.dominios.DomainNode"><id-muni>77</id-muni><patron>2</patron><first-term>Modificar</first-term><id-node>707</id-node><id-des>294</id-des><h-dict xsi:type="java:org.exolab.castor.mapping.MapItem"><key xsi:type="java:java.lang.String">gl_ES</key><value xsi:type="java:java.lang.String">Modificar</value></h-dict><h-dict xsi:type="java:org.exolab.castor.mapping.MapItem"><key xsi:type="java:java.lang.String">es_ES</key><value xsi:type="java:java.lang.String">Modificar</value></h-dict><h-dict xsi:type="java:org.exolab.castor.mapping.MapItem"><key xsi:type="java:java.lang.String">va_ES</key><value xsi:type="java:java.lang.String">Modificar</value></h-dict><h-dict xsi:type="java:org.exolab.castor.mapping.MapItem"><key xsi:type="java:java.lang.String">ca_ES</key><value xsi:type="java:java.lang.String">Modificar</value></h-dict><id-domain>145</id-domain><l-hijos/></value></lista><lista-sorted-by-patron force-delete="false" type="7" xsi:type="java:com.geopista.protocol.administrador.dominios.DomainNode" xmlns:xsi="http://www.w3.org/2001/XMLSchema-instance"><id-muni>77</id-muni><patron>0</patron><first-term>Engadir</first-term><id-node>709</id-node><id-des>296</id-des><h-dict xsi:type="java:org.exolab.castor.mapping.MapItem"><key xsi:type="java:java.lang.String">gl_ES</key><value xsi:type="java:java.lang.String">Engadir</value></h-dict><h-dict xsi:type="java:org.exolab.castor.mapping.MapItem"><key xsi:type="java:java.lang.String">es_ES</key><value xsi:type="java:java.lang.String">Añadir</value></h-dict><h-dict xsi:type="java:org.exolab.castor.mapping.MapItem"><key xsi:type="java:java.lang.String">va_ES</key><value xsi:type="java:java.lang.String">Afegir</value></h-dict><h-dict xsi:type="java:org.exolab.castor.mapping.MapItem"><key xsi:type="java:java.lang.String">ca_ES</key><value xsi:type="java:java.lang.String">Afegir</value></h-dict><id-domain>145</id-domain><l-hijos/></lista-sorted-by-patron><lista-sorted-by-patron force-delete="false" type="7" xsi:type="java:com.geopista.protocol.administrador.dominios.DomainNode" xmlns:xsi="http://www.w3.org/2001/XMLSchema-instance"><id-muni>77</id-muni><patron>1</patron><first-term>Borrar</first-term><id-node>708</id-node><id-des>295</id-des><h-dict xsi:type="java:org.exolab.castor.mapping.MapItem"><key xsi:type="java:java.lang.String">gl_ES</key><value xsi:type="java:java.lang.String">Borrar</value></h-dict><h-dict xsi:type="java:org.exolab.castor.mapping.MapItem"><key xsi:type="java:java.lang.String">es_ES</key><value xsi:type="java:java.lang.String">Borrar</value></h-dict><h-dict xsi:type="java:org.exolab.castor.mapping.MapItem"><key xsi:type="java:java.lang.String">va_ES</key><value xsi:type="java:java.lang.String">Esborrar</value></h-dict><h-dict xsi:type="java:org.exolab.castor.mapping.MapItem"><key xsi:type="java:java.lang.String">ca_ES</key><value xsi:type="java:java.lang.String">Esborrar</value></h-dict><id-domain>145</id-domain><l-hijos/></lista-sorted-by-patron><lista-sorted-by-patron force-delete="false" type="7" xsi:type="java:com.geopista.protocol.administrador.dominios.DomainNode" xmlns:xsi="http://www.w3.org/2001/XMLSchema-instance"><id-muni>77</id-muni><patron>2</patron><first-term>Modificar</first-term><id-node>707</id-node><id-des>294</id-des><h-dict xsi:type="java:org.exolab.castor.mapping.MapItem"><key xsi:type="java:java.lang.String">gl_ES</key><value xsi:type="java:java.lang.String">Modificar</value></h-dict><h-dict xsi:type="java:org.exolab.castor.mapping.MapItem"><key xsi:type="java:java.lang.String">es_ES</key><value xsi:type="java:java.lang.String">Modificar</value></h-dict><h-dict xsi:type="java:org.exolab.castor.mapping.MapItem"><key xsi:type="java:java.lang.String">va_ES</key><value xsi:type="java:java.lang.String">Modificar</value></h-dict><h-dict xsi:type="java:org.exolab.castor.mapping.MapItem"><key xsi:type="java:java.lang.String">ca_ES</key><value xsi:type="java:java.lang.String">Modificar</value></h-dict><id-domain>145</id-domain><l-hijos/></lista-sorted-by-patron><lista-sorted-by-patron force-delete="false" type="7" xsi:type="java:com.geopista.protocol.administrador.dominios.DomainNode" xmlns:xsi="http://www.w3.org/2001/XMLSchema-instance"><id-muni>77</id-muni><patron>3</patron><first-term>Anotación</first-term><id-node>714</id-node><id-des>318</id-des><h-dict xsi:type="java:org.exolab.castor.mapping.MapItem"><key xsi:type="java:java.lang.String">gl_ES</key><value xsi:type="java:java.lang.String">Anotación</value></h-dict><h-dict xsi:type="java:org.exolab.castor.mapping.MapItem"><key xsi:type="java:java.lang.String">es_ES</key><value xsi:type="java:java.lang.String">Anotación</value></h-dict><h-dict xsi:type="java:org.exolab.castor.mapping.MapItem"><key xsi:type="java:java.lang.String">va_ES</key><value xsi:type="java:java.lang.String">Anotació</value></h-dict><h-dict xsi:type="java:org.exolab.castor.mapping.MapItem"><key xsi:type="java:java.lang.String">ca_ES</key><value xsi:type="java:java.lang.String">Anotació</value></h-dict><id-domain>145</id-domain><l-hijos/></lista-sorted-by-patron></lista-estructuras>